odoo/addons/ssi_revenue_recognition_full/README.rst
odoo/addons/ssi_revenue_recognition_full/__init__.py
odoo/addons/ssi_revenue_recognition_full/__manifest__.py
odoo/addons/ssi_revenue_recognition_full/data/approval_template_data.xml
odoo/addons/ssi_revenue_recognition_full/data/ir_sequence_data.xml
odoo/addons/ssi_revenue_recognition_full/data/policy_template_data.xml
odoo/addons/ssi_revenue_recognition_full/data/sequence_template_data.xml
odoo/addons/ssi_revenue_recognition_full/demo/revenue_recognition_full_type_demo.xml
odoo/addons/ssi_revenue_recognition_full/models/__init__.py
odoo/addons/ssi_revenue_recognition_full/models/revenue_recognition_full.py
odoo/addons/ssi_revenue_recognition_full/models/revenue_recognition_full_account.py
odoo/addons/ssi_revenue_recognition_full/models/revenue_recognition_full_type.py
odoo/addons/ssi_revenue_recognition_full/models/revenue_recognition_full_type_account.py
odoo/addons/ssi_revenue_recognition_full/security/ir.model.access.csv
odoo/addons/ssi_revenue_recognition_full/security/ir_module_category_data.xml
odoo/addons/ssi_revenue_recognition_full/security/ir_rule_data.xml
odoo/addons/ssi_revenue_recognition_full/security/res_group_data.xml
odoo/addons/ssi_revenue_recognition_full/static/description/banner.png
odoo/addons/ssi_revenue_recognition_full/static/description/icon.png
odoo/addons/ssi_revenue_recognition_full/views/revenue_recognition_full_type_views.xml
odoo/addons/ssi_revenue_recognition_full/views/revenue_recognition_full_views.xml
odoo14_addon_ssi_revenue_recognition_full-14.0.1.2.2.dev1.dist-info/METADATA
odoo14_addon_ssi_revenue_recognition_full-14.0.1.2.2.dev1.dist-info/WHEEL
odoo14_addon_ssi_revenue_recognition_full-14.0.1.2.2.dev1.dist-info/top_level.txt
odoo14_addon_ssi_revenue_recognition_full-14.0.1.2.2.dev1.dist-info/RECORD
